CHANGELOG.txt
LICENCE.txt
MANIFEST.in
README.txt
setup.py
pytspoker/__init__.py
pytspoker/driver.py
pytspoker/engine.py
pytspoker/six.py
pytspoker/voice.py
pytspoker.egg-info/PKG-INFO
pytspoker.egg-info/SOURCES.txt
pytspoker.egg-info/dependency_links.txt
pytspoker.egg-info/top_level.txt
pytspoker/drivers/__init__.py
pytspoker/drivers/_espeak.py
pytspoker/drivers/dummy.py
pytspoker/drivers/espeak.py
pytspoker/drivers/nsss.py
pytspoker/drivers/sapi5.py