Metadata-Version: 2.1
Name: pytspoker
Version: 0.0.5
Summary: Convert Text to Speech
Home-page: 
Author: Patricia Greer
Author-email: patricia.greer88@outlook.com
License: MIT
Keywords: convert
Classifier: Development Status :: 5 - Production/Stable
Classifier: Intended Audience :: Education
Classifier: Operating System :: Microsoft :: Windows :: Windows 10
Classifier: License :: OSI Approved :: MIT License
Classifier: Programming Language :: Python :: 3
License-File: LICENCE.txt
